RsPulseSeq/RsPulseSeq.py
RsPulseSeq/__init__.py
RsPulseSeq/enums.py
RsPulseSeq/repcap.py
RsPulseSeq/CustomFiles/__init__.py
RsPulseSeq/CustomFiles/events.py
RsPulseSeq/CustomFiles/utilities.py
RsPulseSeq/Implementations/Generator.py
RsPulseSeq/Implementations/MsgLog.py
RsPulseSeq/Implementations/Preview.py
RsPulseSeq/Implementations/Script.py
RsPulseSeq/Implementations/__init__.py
RsPulseSeq/Implementations/Adjustment/Reload.py
RsPulseSeq/Implementations/Adjustment/__init__.py
RsPulseSeq/Implementations/Antenna/__init__.py
RsPulseSeq/Implementations/Antenna/Model/Backlobe.py
RsPulseSeq/Implementations/Antenna/Model/Cardoid.py
RsPulseSeq/Implementations/Antenna/Model/Cosecant.py
RsPulseSeq/Implementations/Antenna/Model/Dipole.py
RsPulseSeq/Implementations/Antenna/Model/Horn.py
RsPulseSeq/Implementations/Antenna/Model/Parabolic.py
RsPulseSeq/Implementations/Antenna/Model/Rotation.py
RsPulseSeq/Implementations/Antenna/Model/__init__.py
RsPulseSeq/Implementations/Antenna/Model/Array/Cosn.py
RsPulseSeq/Implementations/Antenna/Model/Array/Distribution.py
RsPulseSeq/Implementations/Antenna/Model/Array/Element.py
RsPulseSeq/Implementations/Antenna/Model/Array/Pedestal.py
RsPulseSeq/Implementations/Antenna/Model/Array/__init__.py
RsPulseSeq/Implementations/Antenna/Model/Carray/Circular.py
RsPulseSeq/Implementations/Antenna/Model/Carray/Cosn.py
RsPulseSeq/Implementations/Antenna/Model/Carray/Distribution.py
RsPulseSeq/Implementations/Antenna/Model/Carray/Element.py
RsPulseSeq/Implementations/Antenna/Model/Carray/Hexagonal.py
RsPulseSeq/Implementations/Antenna/Model/Carray/Linear.py
RsPulseSeq/Implementations/Antenna/Model/Carray/Pedestal.py
RsPulseSeq/Implementations/Antenna/Model/Carray/Rectangular.py
RsPulseSeq/Implementations/Antenna/Model/Carray/__init__.py
RsPulseSeq/Implementations/Antenna/Model/Custom/HpBw.py
RsPulseSeq/Implementations/Antenna/Model/Custom/__init__.py
RsPulseSeq/Implementations/Antenna/Model/Gaussian/HpBw.py
RsPulseSeq-2.7.1.dist-info/METADATA
RsPulseSeq-2.7.1.dist-info/WHEEL
RsPulseSeq-2.7.1.dist-info/top_level.txt
RsPulseSeq-2.7.1.dist-info/RECORD
